license_api_py/__init__.py
license_api_py/main.py
license_api_py/py.typed
license_api_py-0.1.4.dist-info/METADATA
license_api_py-0.1.4.dist-info/WHEEL
license_api_py-0.1.4.dist-info/licenses/LICENSE
license_api_py-0.1.4.dist-info/RECORD
