Metadata-Version: 2.4
Name: license-api-py
Version: 0.1.4
Summary: License API connector for Python
Author-email: Nazar <je3nsoff@icloud.com>
License-File: LICENSE
Requires-Python: >=3.13
Requires-Dist: httpx>=0.28.1
Requires-Dist: pydantic>=2.11.7
